Workbook

Sheet Historical data
B1: Operating revenue | C1: Operating Profit (EBIT) | D1: Net Profit (PAT) | E1: Depreciation | F1: CapEx | G1: Change in working capital | H1: NOPAT Assuming tax rate at 25% | I1: Free cash flow | J1: EBIT Margin | K1: Depreciation to sale ratio | L1: WC % of Revenue
A2: FY25 | B2: 63121 | C2: 14843 | D2: 10671 | E2: 1355 | F2: 1149 | G2: -554 | H2: =C2*(1-25%) -> 11132.25 | I2: =H2+E2-F2-G2 -> 11892.25 | J2: =C2/B2 -> 0.23515153 | K2: =E2/B2 -> 0.021466707 | L2: =G2/B2 -> -0.0087767938
A3: FY24 | B3: 61896 | C3: 14659 | D3: 10282 | E3: 1216 | F3: 1318 | G3: 1136 | H3: =C3*(1-25%) -> 10994.25 | I3: =H3+E3-F3-G3 -> 9756.25 | J3: =C3/B3 -> 0.23683275 | K3: =E3/B3 -> 0.019645858 | L3: =G3/B3 -> 0.018353367
A4: FY23 | B4: 60580 | C4: 14147 | D4: 10143 | E4: 1137 | F4: 1041 | G4: -863 | H4: =C4*(1-25%) -> 10610.25 | I4: =H4+E4-F4-G4 -> 11569.25 | J4: =C4/B4 -> 0.23352592 | K4: =E4/B4 -> 0.01876857 | L4: =G4/B4 -> -0.014245626
A5: FY22 | B5: 52446 | C5: 12857 | D5: 8892 | E5: 1091 | F5: 919 | G5: -789 | H5: =C5*(1-25%) -> 9642.75 | I5: =H5+E5-F5-G5 -> 10603.75 | J5: =C5/B5 -> 0.24514739 | K5: =E5/B5 -> 0.020802349 | L5: =G5/B5 -> -0.015044045
A6: FY21 | B6: 47028 | C6: 11626 | D6: 7999 | E6: 1074 | F6: 4051 | G6: -56 | H6: =C6*(1-25%) -> 8719.5 | I6: =H6+E6-F6-G6 -> 5798.5 | J6: =C6/B6 -> 0.24721443 | K6: =E6/B6 -> 0.022837459 | L6: =G6/B6 -> -0.00119078
A7: FY20 | B7: 39783 | C7: 9861 | D7: 6756 | E7: 1002 | F7: 765 | G7: 297 | H7: =C7*(1-25%) -> 7395.75 | I7: =H7+E7-F7-G7 -> 7335.75 | J7: =C7/B7 -> 0.24786969 | K7: =E7/B7 -> 0.025186638 | L7: =G7/B7 -> 0.0074655003

Sheet Forecasting assumption
B1: Future revenue assuming growth rate at 5% | C1: Future EBIT assuming at 24% | D1: NOPAT Assuming tax rate at 25% | E1: Depreciation (avg i.e., 1.9%) | F1: Future CapEx Assuming at 5% | G1: WC change (avg i.e, -0.4%) | H1: Free Cash Flow | I1: PV of FCF | L1: Parameter | M1: Needed From Market
A2: FY26 | B2: ='Historical data'!B2*(1+5%) -> 66277.05 | C2: =B2*24% -> 15906.492 | D2: =C2*(1-25%) -> 11929.869 | E2: =B2*1.9% -> 1259.264 | F2: ='Historical data'!F2*(1+5%) -> 1206.45 | G2: =B2*-0.4% -> -265.1082 | H2: =D2+E2-F2-G2 -> 12247.791 | I2: =H2/(1+'DCF Valuation'!$G$6)^1 -> 10984.885 | L2: Risk-free Rate (10-year G-sec) | M2: 0.0652
A3: FY27 | B3: =B2*(1+5%) -> 69590.903 | C3: =B3*24% -> 16701.817 | D3: =C3*(1-25%) -> 12526.362 | E3: =B3*1.9% -> 1322.2271 | F3: =F2*(1+5%) -> 1266.7725 | G3: =B3*-0.4% -> -278.36361 | H3: =D3+E3-F3-G3 -> 12860.181 | I3: =H3/(1+'DCF Valuation'!$G$6)^2 -> 10344.812 | L3: Beta (HUL stock volatility vs market) | M3: 0.83
A4: FY28 | B4: =B3*(1+5%) -> 73070.448 | C4: =B4*24% -> 17536.907 | D4: =C4*(1-25%) -> 13152.681 | E4: =B4*1.9% -> 1388.3385 | F4: =F3*(1+5%) -> 1330.1111 | G4: =B4*-0.4% -> -292.28179 | H4: =D4+E4-F4-G4 -> 13503.19 | I4: =H4/(1+'DCF Valuation'!$G$6)^3 -> 9742.0343 | L4: ERP — Equity Risk Premium India (Assumption) | M4: 0.06
A5: FY29 | B5: =B4*(1+5%) -> 76723.97 | C5: =B5*24% -> 18413.753 | D5: =C5*(1-25%) -> 13810.315 | E5: =B5*1.9% -> 1457.7554 | F5: =F4*(1+5%) -> 1396.6167 | G5: =B5*-0.4% -> -306.89588 | H5: =D5+E5-F5-G5 -> 14178.349 | I5: =H5/(1+'DCF Valuation'!$G$6)^4 -> 9174.3798 | L5: Market Cap | M5: 5.78 lakh crore
A6: FY30 | B6: =B5*(1+5%) -> 80560.169 | C6: =B6*24% -> 19334.44 | D6: =C6*(1-25%) -> 14500.83 | E6: =B6*1.9% -> 1530.6432 | F6: =F5*(1+5%) -> 1466.4475 | G6: =B6*-0.4% -> -322.24067 | H6: =D6+E6-F6-G6 -> 14887.267 | I6: =H6/(1+'DCF Valuation'!$G$6)^5 -> 8639.8017 | L6: Total Debt | M6: almost 0
L7: Tax rate Assuming | M7: 0.25

Sheet DCF Valuation
B1: Free Cash Flow | C1: PV of FCF | F1: Parameter | G1: Calculated values
A2: FY26 | B2: ='Forecasting assumption'!D2+'Forecasting assumption'!E2-'Forecasting assumption'!F2-'Forecasting assumption'!G2 -> 12247.791 | C2: =B2/(1+$G$6)^1 -> 10984.885 | F2: Cost of equity | G2: =('Forecasting assumption'!M2)+'Forecasting assumption'!M3*'Forecasting assumption'!M4 -> 0.115
A3: FY27 | B3: ='Forecasting assumption'!D3+'Forecasting assumption'!E3-'Forecasting assumption'!F3-'Forecasting assumption'!G3 -> 12860.181 | C3: =B3/(1+$G$6)^2 -> 10344.812 | F3: Cost of Debt % | G3: =7%*(1-25%) -> 0.0525
A4: FY28 | B4: ='Forecasting assumption'!D4+'Forecasting assumption'!E4-'Forecasting assumption'!F4-'Forecasting assumption'!G4 -> 13503.19 | C4: =B4/(1+$G$6)^3 -> 9742.0343 | F4: We | G4: =578000/(578000+300) -> 0.99948124
A5: FY29 | B5: ='Forecasting assumption'!D5+'Forecasting assumption'!E5-'Forecasting assumption'!F5-'Forecasting assumption'!G5 -> 14178.349 | C5: =B5/(1+$G$6)^4 -> 9174.3798 | F5: Wd | G5: =300/(578000+300) -> 0.00051876189
A6: FY30 | B6: ='Forecasting assumption'!D6+'Forecasting assumption'!E6-'Forecasting assumption'!F6-'Forecasting assumption'!G6 -> 14887.267 | C6: =B6/(1+$G$6)^5 -> 8639.8017 | F6: WACC | G6: =G4*G2+(G5*G3) -> 0.11496758
F7: Growth assumption | G7: 0.04
C9: Terminal Value | D9: ='Forecasting assumption'!H6*(1+G7)/(G6-G7) -> 206526.05
C10: PV of terminal Value | D10: =D9/(1+'DCF Valuation'!G6)^5 -> 119857.06
B11: Interinsic equity value | C11: Enterprise value | D11: =(SUM('Forecasting assumption'!I2:I6))+D10 -> 168742.98
C12: Interinsic price | D12: =D11/235 -> 718.05523 | E12: HUL shares ≈ 235 Cr shares

Sheet Sensitivity Analysis
B1: PV of FCF (Years 1–5) | C1: 48886
B2: FCF in Final Year (Year 5) | C2: 14887
B3: WACC | C3: 0.115
B4: Growth (g) | C4: 0.04
B6: Enterprise Value (EV) | C6: =$C$1 +( ($C$2 * (1 + C$4) / (C3 - C$4) ) / (1 + C3)^5) -> 168671.69
B9: =C6 -> 168671.69 | C9: 0.03 | D9: 0.04 | E9: 0.05 | F9: 0.06
B10: 0.08 | C10: 257601.95 | D10: 312313.89 | E10: 403500.47 | F10: 585873.63
B11: 0.09 | C11: 214982.57 | D11: 250136.99 | E11: 302868.62 | F11: 390754.68
B12: 0.1 | C12: 184899.79 | D12: 209109.37 | E12: 243002.77 | F12: 293842.88
B13: 0.115 | C13: 153562.97 | D13: 168671.69 | E13: 188429.24 | F13: 215371.35
B14: 0.12 | C14: 145560.47 | D14: 158700.69 | E14: 175595.25 | F14: 198121.34

Sheet DCF Summary
A1: EXECUTIVE SUMMARY
A3: HUL Valuation Summary – DCF Approach
A5: This discounted cash flow model estimates the intrinsic value of Hindustan Unilever Limited (HUL) based on projected free cash flows for FY26–FY30 and a terminal value calculated using long-term growth assumptions. Sensitivity analysis across various WACC and terminal growth scenarios has been included to ensure robustness.
A7: KEY ASSUMPTIONS TABLE
A9: Category | B9: Assumption
A10: Forecast Period | B10: 5 Years (FY26–FY30)
A11: Revenue Growth | B11: 5% per annum
A12: EBIT Margin | B12: 0.24
A13: Tax Rate | B13: 0.25
A14: Depreciation | B14: 1.9% of revenue
A15: CapEx Growth | B15: 5% per annum
A16: WC Change | B16: –0.4% of revenue
A17: Final Year FCF | B17: ₹14,887 crore
A18: WACC (Base Case) | B18: 0.115
A19: Terminal Growth (g) | B19: 0.04
A21: VALUATION OUTPUT
A23: Metric | B23: Value (₹ Crore)
A24: PV of Free Cash Flows (FY26–FY30) | B24: 48886
A25: PV of Terminal Value | B25: 119786
A26: Enterprise Value (EV) | B26: 168672
A27: Net Debt (Negative = Net Cash) | B27: –5,585
A28: Equity Value | B28: 174257
A29: Shares Outstanding (Crore) | B29: 234.95
A30: Intrinsic Value Per Share (₹) | B30: 742
A32: SENSITIVITY ANALYSIS
A34: ='Sensitivity Analysis'!C6 -> 168671.69 | B34: Growth Rate =3% | C34: Growth rate =4% | D34: Growth rate =5% | E34: Growth rate =6%
A35: WACC=8% | B35: 257601.95 | C35: 312313.89 | D35: 403500.47 | E35: 585873.63
A36: WACC=9% | B36: 214982.57 | C36: 250136.99 | D36: 302868.62 | E36: 390754.68
A37: WACC=10% | B37: 184899.79 | C37: 209109.37 | D37: 243002.77 | E37: 293842.88
A38: WACC=11.5% | B38: 153562.97 | C38: 168671.69 | D38: 188429.24 | E38: 215371.35
A39: WACC=12% | B39: 145560.47 | C39: 158700.69 | D39: 175595.25 | E39: 198121.34
A41: Valuation Conclusion
A43: Under the base-case assumptions (WACC: 11.5%, terminal growth: 4%), the DCF-derived intrinsic value is lower than the current market price. However, sensitivity analysis indicates that the market valuation of HUL can be justified under scenarios involving a lower cost of capital and/or higher long-term growth assumptions.
A45: This suggests that current market prices embed a premium for HUL’s strong brand equity, predictable cash flows, and lower perceived business risk, positioning the stock as a long-duration, defensive compounder rather than a valuation-driven opportunity.

Sheet PB_Valuation_Summary
A1: Metrics | B1: Values
A2: Company Name | B2: Hindustan Unilever Limited (HUL)
A3: Valuation Method | B3: DCF (FCFF)
A4: Forecast Period (Years) | B4: 6
A5: WACC (%) | B5: ='DCF Summary'!B18 -> 0.115
A6: Terminal Growth (%) | B6: ='DCF Summary'!B19 -> 0.04
A7: Intrinsic Value per Share (₹) | B7: ='DCF Summary'!B30 -> 742
A8: Current Market Price (₹) | B8: 2450
A9: Upside / Downside vs Market (%) | B9: =(B7-B8)/B8 -> -0.69714286

Sheet PB_Cashflow_Drivers
A1: Year | B1: Period Type | C1: Revenue (₹ Cr) | D1: Free Cash Flow – FCFF (₹ Cr)
A2: ='Historical data'!A7 -> FY20 | B2: Historical | C2: ='Historical data'!B7 -> 39783 | D2: ='Historical data'!I7 -> 7335.75
A3: ='Historical data'!A6 -> FY21 | B3: Historical | C3: ='Historical data'!B6 -> 47028 | D3: ='Historical data'!I6 -> 5798.5
A4: ='Historical data'!A5 -> FY22 | B4: Historical | C4: ='Historical data'!B5 -> 52446 | D4: ='Historical data'!I5 -> 10603.75
A5: ='Historical data'!A4 -> FY23 | B5: Historical | C5: ='Historical data'!B4 -> 60580 | D5: ='Historical data'!I4 -> 11569.25
A6: ='Historical data'!A3 -> FY24 | B6: Historical | C6: ='Historical data'!B3 -> 61896 | D6: ='Historical data'!I3 -> 9756.25
A7: ='Historical data'!A2 -> FY25 | B7: Historical | C7: ='Historical data'!B2 -> 63121 | D7: ='Historical data'!I2 -> 11892.25
A8: ='Forecasting assumption'!A2 -> FY26 | B8: Forecast | C8: ='Forecasting assumption'!B2 -> 66277.05 | D8: ='Forecasting assumption'!H2 -> 12247.791
A9: ='Forecasting assumption'!A3 -> FY27 | B9: Forecast | C9: ='Forecasting assumption'!B3 -> 69590.903 | D9: ='Forecasting assumption'!H3 -> 12860.181
A10: ='Forecasting assumption'!A4 -> FY28 | B10: Forecast | C10: ='Forecasting assumption'!B4 -> 73070.448 | D10: ='Forecasting assumption'!H4 -> 13503.19
A11: ='Forecasting assumption'!A5 -> FY29 | B11: Forecast | C11: ='Forecasting assumption'!B5 -> 76723.97 | D11: ='Forecasting assumption'!H5 -> 14178.349
A12: ='Forecasting assumption'!A6 -> FY30 | B12: Forecast | C12: ='Forecasting assumption'!B6 -> 80560.169 | D12: ='Forecasting assumption'!H6 -> 14887.267

Sheet PB_Sensitivity
A1: WACC (%) | B1: Terminal Growth (%) | C1: Enterprise Value (₹ Cr)
A2: 12 | B2: 3 | C2: 145560.47
A3: 11.5 | B3: 3 | C3: 153562.97
A4: 10 | B4: 3 | C4: 184899.79
A5: 9 | B5: 3 | C5: 214982.57
A6: 8 | B6: 3 | C6: 257601.95
A7: 12 | B7: 4 | C7: 158700.69
A8: 11.5 | B8: 4 | C8: 168671.69
A9: 10 | B9: 4 | C9: 209109.37
A10: 9 | B10: 4 | C10: 250136.99
A11: 8 | B11: 4 | C11: 312313.89
A12: 12 | B12: 5 | C12: 175595.25
A13: 11.5 | B13: 5 | C13: 188429.24
... A21: 8 | B21: 6 | C21: 585873.63

Sheet Sheet2
A1: Your model shows a big downside. Why?”
A3: You answer:
A5: “My base-case DCF uses a WACC of 11.5% and terminal growth of 4%, which results in an intrinsic value of around ₹742 per share. The sensitivity analysis shows that the current market price can be justified under lower discount rates or higher terminal growth, indicating that the market is pricing HUL as a low-risk, long-duration cash-flow business.”
